{"meta":{"colorings":[{"key":"country","title":"Country","type":"categorical"},{"key":"cluster","title":"cluster","type":"categorical"}],"description":"JSON generated by matUtils. If you have metadata you wish to display, you can now drag on a CSV/TSV file and it will be added into this view, [see here](https://docs.nextstrain.org/projects/auspice/en/latest/advanced-functionality/drag-drop-csv-tsv.html) for more info.","display_defaults":{"branch_label":"none"},"filters":["country"],"panels":["tree"],"title":"mutation_annotated_tree"},"tree":{"children":[{"branch_attrs":{"labels":{"nuc mutations":"G210T,C241T,C3037T,G4181T,C6040T,C6402T,C6638T,C7124T,C7926T,C8986T,G9053T,C10029T,A11201G,A11332G,T14014G,C14408T,G15451A,C16466T,C16726T,C19220T,C21618G,T22917G,C22995A,A23403G,C23604G,G24410A,C25469T,C26537T,T26767C,T27638C,C27752T,C27874T,G28073T,G28248A,A28461G,G28881T,G28916T,G29402T,A29700G,G29742T","sample":"node_18294"},"mutations":{"nuc":["G210T","C241T","C3037T","G4181T","C6040T","C6402T","C6638T","C7124T","C7926T","C8986T","G9053T","C10029T","A11201G","A11332G","T14014G","C14408T","G15451A","C16466T","C16726T","C19220T","C21618G","T22917G","C22995A","A23403G","C23604G","G24410A","C25469T","C26537T","T26767C","T27638C","C27752T","C27874T","G28073T","G28248A","A28461G","G28881T","G28916T","G29402T","A29700G","G29742T"]}},"children":[{"branch_attrs":{"labels":{"cluster":"node_18294","nuc mutations":"G4148T,T27534C,C28677T","sample":"USA/UT-UPHL-210722453574/2021|MZ732010.1|2021-07-07"},"mutations":{"nuc":["G4148T","T27534C","C28677T"]}},"name":"USA/UT-UPHL-210722453574/2021|MZ732010.1|2021-07-07","node_attrs":{"MAT_Clade_0":{"value":""},"MAT_Clade_1":{"value":""},"cluster":{"value":"node_18294"},"country":{"value":"USA"},"date":{"value":"2021-07-07"},"div":43}},{"branch_attrs":{"labels":{"cluster":"node_18294","nuc mutations":"C28695T,C29421T","sample":"USA/UT-UPHL-210806103244/2021|MZ834732.1|2021-07-26"},"mutations":{"nuc":["C28695T","C29421T"]}},"name":"USA/UT-UPHL-210806103244/2021|MZ834732.1|2021-07-26","node_attrs":{"MAT_Clade_0":{"value":""},"MAT_Clade_1":{"value":""},"cluster":{"value":"node_18294"},"country":{"value":"USA"},"date":{"value":"2021-07-26"},"div":42}},{"branch_attrs":{"labels":{"cluster":"node_18294","nuc mutations":"C16260T","sample":"USA/UT-UPHL-210806425760/2021|MZ834931.1|2021-07-22"},"mutations":{"nuc":["C16260T"]}},"name":"USA/UT-UPHL-210806425760/2021|MZ834931.1|2021-07-22","node_attrs":{"MAT_Clade_0":{"value":""},"MAT_Clade_1":{"value":""},"cluster":{"value":"node_18294"},"country":{"value":"USA"},"date":{"value":"2021-07-22"},"div":41}},{"branch_attrs":{"labels":{"cluster":"node_18294","nuc mutations":"T7124C","sample":"USA/UT-UPHL-210806745666/2021|MZ835116.1|2021-07-22"},"mutations":{"nuc":["T7124C"]}},"name":"USA/UT-UPHL-210806745666/2021|MZ835116.1|2021-07-22","node_attrs":{"MAT_Clade_0":{"value":""},"MAT_Clade_1":{"value":""},"cluster":{"value":"node_18294"},"country":{"value":"USA"},"date":{"value":"2021-07-22"},"div":41}},{"branch_attrs":{"labels":{"cluster":"node_18294","nuc mutations":"","sample":"USA/UT-CDC-2-4718234/2021|MZ828394.1|2021-07-22"},"mutations":{"nuc":[]}},"name":"USA/UT-CDC-2-4718234/2021|MZ828394.1|2021-07-22","node_attrs":{"MAT_Clade_0":{"value":""},"MAT_Clade_1":{"value":""},"cluster":{"value":"node_18294"},"country":{"value":"USA"},"date":{"value":"2021-07-22"},"div":40}},{"branch_attrs":{"labels":{"nuc mutations":"C11758T","sample":"node_18303"},"mutations":{"nuc":["C11758T"]}},"children":[{"branch_attrs":{"labels":{"cluster":"node_18294","nuc mutations":"","sample":"USA/UT-UPHL-210729220135/2021|MZ746247.1|2021-07-21"},"mutations":{"nuc":[]}},"name":"USA/UT-UPHL-210729220135/2021|MZ746247.1|2021-07-21","node_attrs":{"MAT_Clade_0":{"value":""},"MAT_Clade_1":{"value":""},"cluster":{"value":"node_18294"},"country":{"value":"USA"},"date":{"value":"2021-07-21"},"div":41}},{"branch_attrs":{"labels":{"cluster":"node_18294","nuc mutations":"","sample":"USA/UT-UPHL-210729220135/2021|MZ770284.1|2021-07-21"},"mutations":{"nuc":[]}},"name":"USA/UT-UPHL-210729220135/2021|MZ770284.1|2021-07-21","node_attrs":{"MAT_Clade_0":{"value":""},"MAT_Clade_1":{"value":""},"cluster":{"value":"node_18294"},"country":{"value":"USA"},"date":{"value":"2021-07-21"},"div":41}}],"name":"node_18303","node_attrs":{"div":41}},{"branch_attrs":{"labels":{"nuc mutations":"C14120T,C20703T","sample":"node_18301"},"mutations":{"nuc":["C14120T","C20703T"]}},"children":[{"branch_attrs":{"labels":{"cluster":"node_18294","nuc mutations":"","sample":"USA/UT-UPHL-210722717037/2021|MZ732061.1|2021-07-13"},"mutations":{"nuc":[]}},"name":"USA/UT-UPHL-210722717037/2021|MZ732061.1|2021-07-13","node_attrs":{"MAT_Clade_0":{"value":""},"MAT_Clade_1":{"value":""},"cluster":{"value":"node_18294"},"country":{"value":"USA"},"date":{"value":"2021-07-13"},"div":42}},{"branch_attrs":{"labels":{"cluster":"node_18294","nuc mutations":"","sample":"USA/UT-UPHL-210723025496/2021|MZ683512.1|2021-07-15"},"mutations":{"nuc":[]}},"name":"USA/UT-UPHL-210723025496/2021|MZ683512.1|2021-07-15","node_attrs":{"MAT_Clade_0":{"value":""},"MAT_Clade_1":{"value":""},"cluster":{"value":"node_18294"},"country":{"value":"USA"},"date":{"value":"2021-07-15"},"div":42}},{"branch_attrs":{"labels":{"cluster":"node_18294","nuc mutations":"","sample":"USA/UT-UPHL-210722018905/2021|MZ731938.1|2021-07-13"},"mutations":{"nuc":[]}},"name":"USA/UT-UPHL-210722018905/2021|MZ731938.1|2021-07-13","node_attrs":{"MAT_Clade_0":{"value":""},"MAT_Clade_1":{"value":""},"cluster":{"value":"node_18294"},"country":{"value":"USA"},"date":{"value":"2021-07-13"},"div":42}},{"branch_attrs":{"labels":{"cluster":"node_18294","nuc mutations":"","sample":"USA/UT-UPHL-210722748743/2021|MZ732071.1|2021-07-13"},"mutations":{"nuc":[]}},"name":"USA/UT-UPHL-210722748743/2021|MZ732071.1|2021-07-13","node_attrs":{"MAT_Clade_0":{"value":""},"MAT_Clade_1":{"value":""},"cluster":{"value":"node_18294"},"country":{"value":"USA"},"date":{"value":"2021-07-13"},"div":42}}],"name":"node_18301","node_attrs":{"div":42}},{"branch_attrs":{"labels":{"nuc mutations":"C843T","sample":"node_18302"},"mutations":{"nuc":["C843T"]}},"children":[{"branch_attrs":{"labels":{"cluster":"node_18294","nuc mutations":"","sample":"USA/UT-UPHL-210729637684/2021|MZ746474.1|2021-07-19"},"mutations":{"nuc":[]}},"name":"USA/UT-UPHL-210729637684/2021|MZ746474.1|2021-07-19","node_attrs":{"MAT_Clade_0":{"value":""},"MAT_Clade_1":{"value":""},"cluster":{"value":"node_18294"},"country":{"value":"USA"},"date":{"value":"2021-07-19"},"div":41}},{"branch_attrs":{"labels":{"cluster":"node_18294","nuc mutations":"","sample":"USA/UT-UPHL-210729874755/2021|MZ746593.1|2021-07-19"},"mutations":{"nuc":[]}},"name":"USA/UT-UPHL-210729874755/2021|MZ746593.1|2021-07-19","node_attrs":{"MAT_Clade_0":{"value":""},"MAT_Clade_1":{"value":""},"cluster":{"value":"node_18294"},"country":{"value":"USA"},"date":{"value":"2021-07-19"},"div":41}},{"branch_attrs":{"labels":{"cluster":"node_18294","nuc mutations":"","sample":"USA/UT-UPHL-210729874755/2021|MZ770631.1|2021-07-19"},"mutations":{"nuc":[]}},"name":"USA/UT-UPHL-210729874755/2021|MZ770631.1|2021-07-19","node_attrs":{"MAT_Clade_0":{"value":""},"MAT_Clade_1":{"value":""},"cluster":{"value":"node_18294"},"country":{"value":"USA"},"date":{"value":"2021-07-19"},"div":41}},{"branch_attrs":{"labels":{"cluster":"node_18294","nuc mutations":"","sample":"USA/UT-UPHL-210729637684/2021|MZ770512.1|2021-07-19"},"mutations":{"nuc":[]}},"name":"USA/UT-UPHL-210729637684/2021|MZ770512.1|2021-07-19","node_attrs":{"MAT_Clade_0":{"value":""},"MAT_Clade_1":{"value":""},"cluster":{"value":"node_18294"},"country":{"value":"USA"},"date":{"value":"2021-07-19"},"div":41}}],"name":"node_18302","node_attrs":{"div":41}},{"branch_attrs":{"labels":{"nuc mutations":"A6139G","sample":"node_18295"},"mutations":{"nuc":["A6139G"]}},"children":[{"branch_attrs":{"labels":{"cluster":"node_18294","nuc mutations":"G29700A","sample":"USA/UT-CDC-LC0102526/2021|MZ783867.1|2021-07-09"},"mutations":{"nuc":["G29700A"]}},"name":"USA/UT-CDC-LC0102526/2021|MZ783867.1|2021-07-09","node_attrs":{"MAT_Clade_0":{"value":""},"MAT_Clade_1":{"value":""},"cluster":{"value":"node_18294"},"country":{"value":"USA"},"date":{"value":"2021-07-09"},"div":42}},{"branch_attrs":{"labels":{"cluster":"node_18294","nuc mutations":"C21806T","sample":"USA/UT-UPHL-210806181733/2021|MZ834795.1|2021-07-23"},"mutations":{"nuc":["C21806T"]}},"name":"USA/UT-UPHL-210806181733/2021|MZ834795.1|2021-07-23","node_attrs":{"MAT_Clade_0":{"value":""},"MAT_Clade_1":{"value":""},"cluster":{"value":"node_18294"},"country":{"value":"USA"},"date":{"value":"2021-07-23"},"div":42}},{"branch_attrs":{"labels":{"cluster":"node_18294","nuc mutations":"G1444T","sample":"USA/UT-UPHL-210723899318/2021|MZ683825.1|2021-07-13"},"mutations":{"nuc":["G1444T"]}},"name":"USA/UT-UPHL-210723899318/2021|MZ683825.1|2021-07-13","node_attrs":{"MAT_Clade_0":{"value":""},"MAT_Clade_1":{"value":""},"cluster":{"value":"node_18294"},"country":{"value":"USA"},"date":{"value":"2021-07-13"},"div":42}},{"branch_attrs":{"labels":{"cluster":"node_18294","nuc mutations":"","sample":"USA/UT-UPHL-210722848082/2021|MZ732089.1|2021-07-09"},"mutations":{"nuc":[]}},"name":"USA/UT-UPHL-210722848082/2021|MZ732089.1|2021-07-09","node_attrs":{"MAT_Clade_0":{"value":""},"MAT_Clade_1":{"value":""},"cluster":{"value":"node_18294"},"country":{"value":"USA"},"date":{"value":"2021-07-09"},"div":41}},{"branch_attrs":{"labels":{"cluster":"node_18294","nuc mutations":"","sample":"USA/UT-UPHL-210729002943/2021|MZ746140.1|2021-07-19"},"mutations":{"nuc":[]}},"name":"USA/UT-UPHL-210729002943/2021|MZ746140.1|2021-07-19","node_attrs":{"MAT_Clade_0":{"value":""},"MAT_Clade_1":{"value":""},"cluster":{"value":"node_18294"},"country":{"value":"USA"},"date":{"value":"2021-07-19"},"div":41}},{"branch_attrs":{"labels":{"cluster":"node_18294","nuc mutations":"","sample":"USA/UT-UPHL-210722896424/2021|MZ732097.1|2021-07-09"},"mutations":{"nuc":[]}},"name":"USA/UT-UPHL-210722896424/2021|MZ732097.1|2021-07-09","node_attrs":{"MAT_Clade_0":{"value":""},"MAT_Clade_1":{"value":""},"cluster":{"value":"node_18294"},"country":{"value":"USA"},"date":{"value":"2021-07-09"},"div":41}},{"branch_attrs":{"labels":{"nuc mutations":"","sample":"USA/CA-CDC-FG-061692/2021|MZ763856.1|2021-08-04"},"mutations":{"nuc":[]}},"name":"USA/CA-CDC-FG-061692/2021|MZ763856.1|2021-08-04","node_attrs":{"MAT_Clade_0":{"value":""},"MAT_Clade_1":{"value":""},"country":{"value":"USA"},"date":{"value":"2021-08-04"},"div":41}},{"branch_attrs":{"labels":{"nuc mutations":"","sample":"USA/CA-CDC-FG-061684/2021|MZ763855.1|2021-08-04"},"mutations":{"nuc":[]}},"name":"USA/CA-CDC-FG-061684/2021|MZ763855.1|2021-08-04","node_attrs":{"MAT_Clade_0":{"value":""},"MAT_Clade_1":{"value":""},"country":{"value":"USA"},"date":{"value":"2021-08-04"},"div":41}},{"branch_attrs":{"labels":{"cluster":"node_18294","nuc mutations":"","sample":"USA/UT-UPHL-210729328756/2021|MZ746298.1|2021-07-21"},"mutations":{"nuc":[]}},"name":"USA/UT-UPHL-210729328756/2021|MZ746298.1|2021-07-21","node_attrs":{"MAT_Clade_0":{"value":""},"MAT_Clade_1":{"value":""},"cluster":{"value":"node_18294"},"country":{"value":"USA"},"date":{"value":"2021-07-21"},"div":41}},{"branch_attrs":{"labels":{"cluster":"node_18294","nuc mutations":"","sample":"USA/UT-UPHL-210722577258/2021|MZ732031.1|2021-07-12"},"mutations":{"nuc":[]}},"name":"USA/UT-UPHL-210722577258/2021|MZ732031.1|2021-07-12","node_attrs":{"MAT_Clade_0":{"value":""},"MAT_Clade_1":{"value":""},"cluster":{"value":"node_18294"},"country":{"value":"USA"},"date":{"value":"2021-07-12"},"div":41}},{"branch_attrs":{"labels":{"cluster":"node_18294","nuc mutations":"","sample":"USA/UT-UPHL-210731417696/2021|MZ769448.1|2021-07-20"},"mutations":{"nuc":[]}},"name":"USA/UT-UPHL-210731417696/2021|MZ769448.1|2021-07-20","node_attrs":{"MAT_Clade_0":{"value":""},"MAT_Clade_1":{"value":""},"cluster":{"value":"node_18294"},"country":{"value":"USA"},"date":{"value":"2021-07-20"},"div":41}},{"branch_attrs":{"labels":{"cluster":"node_18294","nuc mutations":"","sample":"USA/UT-UPHL-210729002943/2021|MZ770176.1|2021-07-19"},"mutations":{"nuc":[]}},"name":"USA/UT-UPHL-210729002943/2021|MZ770176.1|2021-07-19","node_attrs":{"MAT_Clade_0":{"value":""},"MAT_Clade_1":{"value":""},"cluster":{"value":"node_18294"},"country":{"value":"USA"},"date":{"value":"2021-07-19"},"div":41}},{"branch_attrs":{"labels":{"cluster":"node_18294","nuc mutations":"","sample":"USA/UT-UPHL-210731635432/2021|MZ769474.1|2021-07-21"},"mutations":{"nuc":[]}},"name":"USA/UT-UPHL-210731635432/2021|MZ769474.1|2021-07-21","node_attrs":{"MAT_Clade_0":{"value":""},"MAT_Clade_1":{"value":""},"cluster":{"value":"node_18294"},"country":{"value":"USA"},"date":{"value":"2021-07-21"},"div":41}},{"branch_attrs":{"labels":{"cluster":"node_18294","nuc mutations":"","sample":"USA/UT-UPHL-210729328756/2021|MZ770335.1|2021-07-21"},"mutations":{"nuc":[]}},"name":"USA/UT-UPHL-210729328756/2021|MZ770335.1|2021-07-21","node_attrs":{"MAT_Clade_0":{"value":""},"MAT_Clade_1":{"value":""},"cluster":{"value":"node_18294"},"country":{"value":"USA"},"date":{"value":"2021-07-21"},"div":41}},{"branch_attrs":{"labels":{"cluster":"node_18294","nuc mutations":"","sample":"USA/UT-UPHL-210811875240/2021|MZ817917.1|2021-07-20"},"mutations":{"nuc":[]}},"name":"USA/UT-UPHL-210811875240/2021|MZ817917.1|2021-07-20","node_attrs":{"MAT_Clade_0":{"value":""},"MAT_Clade_1":{"value":""},"cluster":{"value":"node_18294"},"country":{"value":"USA"},"date":{"value":"2021-07-20"},"div":41}},{"branch_attrs":{"labels":{"cluster":"node_18294","nuc mutations":"","sample":"USA/UT-UPHL-210806147821/2021|MZ834769.1|2021-07-20"},"mutations":{"nuc":[]}},"name":"USA/UT-UPHL-210806147821/2021|MZ834769.1|2021-07-20","node_attrs":{"MAT_Clade_0":{"value":""},"MAT_Clade_1":{"value":""},"cluster":{"value":"node_18294"},"country":{"value":"USA"},"date":{"value":"2021-07-20"},"div":41}},{"branch_attrs":{"labels":{"cluster":"node_18294","nuc mutations":"","sample":"USA/UT-UPHL-210806855029/2021|MZ835188.1|2021-07-11"},"mutations":{"nuc":[]}},"name":"USA/UT-UPHL-210806855029/2021|MZ835188.1|2021-07-11","node_attrs":{"MAT_Clade_0":{"value":""},"MAT_Clade_1":{"value":""},"cluster":{"value":"node_18294"},"country":{"value":"USA"},"date":{"value":"2021-07-11"},"div":41}},{"branch_attrs":{"labels":{"cluster":"node_18294","nuc mutations":"","sample":"USA/UT-UPHL-210806804144/2021|MZ835153.1|2021-07-06"},"mutations":{"nuc":[]}},"name":"USA/UT-UPHL-210806804144/2021|MZ835153.1|2021-07-06","node_attrs":{"MAT_Clade_0":{"value":""},"MAT_Clade_1":{"value":""},"cluster":{"value":"node_18294"},"country":{"value":"USA"},"date":{"value":"2021-07-06"},"div":41}},{"branch_attrs":{"labels":{"nuc mutations":"C19572T,T23287A,C28507T","sample":"node_18296"},"mutations":{"nuc":["C19572T","T23287A","C28507T"]}},"children":[{"branch_attrs":{"labels":{"nuc mutations":"G7328T","sample":"USA/CA-CDC-FG-056141/2021|MZ765222.1|2021-07-31"},"mutations":{"nuc":["G7328T"]}},"name":"USA/CA-CDC-FG-056141/2021|MZ765222.1|2021-07-31","node_attrs":{"MAT_Clade_0":{"value":""},"MAT_Clade_1":{"value":""},"country":{"value":"USA"},"date":{"value":"2021-07-31"},"div":45}},{"branch_attrs":{"labels":{"nuc mutations":"","sample":"USA/CA-CDC-FG-047717/2021|MZ698788.1|2021-07-22"},"mutations":{"nuc":[]}},"name":"USA/CA-CDC-FG-047717/2021|MZ698788.1|2021-07-22","node_attrs":{"MAT_Clade_0":{"value":""},"MAT_Clade_1":{"value":""},"country":{"value":"USA"},"date":{"value":"2021-07-22"},"div":44}},{"branch_attrs":{"labels":{"cluster":"node_18294","nuc mutations":"","sample":"USA/UT-UPHL-210729756107/2021|MZ746532.1|2021-07-15"},"mutations":{"nuc":[]}},"name":"USA/UT-UPHL-210729756107/2021|MZ746532.1|2021-07-15","node_attrs":{"MAT_Clade_0":{"value":""},"MAT_Clade_1":{"value":""},"cluster":{"value":"node_18294"},"country":{"value":"USA"},"date":{"value":"2021-07-15"},"div":44}},{"branch_attrs":{"labels":{"nuc mutations":"","sample":"USA/CA-CDC-FG-046976/2021|MZ696654.1|2021-07-21"},"mutations":{"nuc":[]}},"name":"USA/CA-CDC-FG-046976/2021|MZ696654.1|2021-07-21","node_attrs":{"MAT_Clade_0":{"value":""},"MAT_Clade_1":{"value":""},"country":{"value":"USA"},"date":{"value":"2021-07-21"},"div":44}},{"branch_attrs":{"labels":{"cluster":"node_18294","nuc mutations":"","sample":"USA/UT-UPHL-210729756107/2021|MZ770570.1|2021-07-15"},"mutations":{"nuc":[]}},"name":"USA/UT-UPHL-210729756107/2021|MZ770570.1|2021-07-15","node_attrs":{"MAT_Clade_0":{"value":""},"MAT_Clade_1":{"value":""},"cluster":{"value":"node_18294"},"country":{"value":"USA"},"date":{"value":"2021-07-15"},"div":44}},{"branch_attrs":{"labels":{"cluster":"node_18294","nuc mutations":"","sample":"USA/UT-UPHL-210806132958/2021|MZ834761.1|2021-07-24"},"mutations":{"nuc":[]}},"name":"USA/UT-UPHL-210806132958/2021|MZ834761.1|2021-07-24","node_attrs":{"MAT_Clade_0":{"value":""},"MAT_Clade_1":{"value":""},"cluster":{"value":"node_18294"},"country":{"value":"USA"},"date":{"value":"2021-07-24"},"div":44}}],"name":"node_18296","node_attrs":{"div":44}},{"branch_attrs":{"labels":{"nuc mutations":"C8311T","sample":"node_18299"},"mutations":{"nuc":["C8311T"]}},"children":[{"branch_attrs":{"labels":{"cluster":"node_18294","nuc mutations":"","sample":"USA/UT-UPHL-210729419384/2021|MZ746338.1|2021-07-14"},"mutations":{"nuc":[]}},"name":"USA/UT-UPHL-210729419384/2021|MZ746338.1|2021-07-14","node_attrs":{"MAT_Clade_0":{"value":""},"MAT_Clade_1":{"value":""},"cluster":{"value":"node_18294"},"country":{"value":"USA"},"date":{"value":"2021-07-14"},"div":42}},{"branch_attrs":{"labels":{"cluster":"node_18294","nuc mutations":"","sample":"USA/UT-UPHL-210729419384/2021|MZ770375.1|2021-07-14"},"mutations":{"nuc":[]}},"name":"USA/UT-UPHL-210729419384/2021|MZ770375.1|2021-07-14","node_attrs":{"MAT_Clade_0":{"value":""},"MAT_Clade_1":{"value":""},"cluster":{"value":"node_18294"},"country":{"value":"USA"},"date":{"value":"2021-07-14"},"div":42}},{"branch_attrs":{"labels":{"nuc mutations":"C26004T","sample":"node_18300"},"mutations":{"nuc":["C26004T"]}},"children":[{"branch_attrs":{"labels":{"cluster":"node_18294","nuc mutations":"","sample":"USA/UT-UPHL-210729815262/2021|MZ746564.1|2021-07-14"},"mutations":{"nuc":[]}},"name":"USA/UT-UPHL-210729815262/2021|MZ746564.1|2021-07-14","node_attrs":{"MAT_Clade_0":{"value":""},"MAT_Clade_1":{"value":""},"cluster":{"value":"node_18294"},"country":{"value":"USA"},"date":{"value":"2021-07-14"},"div":43}},{"branch_attrs":{"labels":{"cluster":"node_18294","nuc mutations":"","sample":"USA/UT-UPHL-210731109017/2021|MZ769406.1|2021-07-21"},"mutations":{"nuc":[]}},"name":"USA/UT-UPHL-210731109017/2021|MZ769406.1|2021-07-21","node_attrs":{"MAT_Clade_0":{"value":""},"MAT_Clade_1":{"value":""},"cluster":{"value":"node_18294"},"country":{"value":"USA"},"date":{"value":"2021-07-21"},"div":43}},{"branch_attrs":{"labels":{"cluster":"node_18294","nuc mutations":"","sample":"USA/UT-UPHL-210729815262/2021|MZ770602.1|2021-07-14"},"mutations":{"nuc":[]}},"name":"USA/UT-UPHL-210729815262/2021|MZ770602.1|2021-07-14","node_attrs":{"MAT_Clade_0":{"value":""},"MAT_Clade_1":{"value":""},"cluster":{"value":"node_18294"},"country":{"value":"USA"},"date":{"value":"2021-07-14"},"div":43}}],"name":"node_18300","node_attrs":{"div":43}}],"name":"node_18299","node_attrs":{"div":42}},{"branch_attrs":{"labels":{"nuc mutations":"T27752C","sample":"node_18297"},"mutations":{"nuc":["T27752C"]}},"children":[{"branch_attrs":{"labels":{"cluster":"node_18294","nuc mutations":"","sample":"USA/UT-UPHL-210729773882/2021|MZ746543.1|2021-07-16"},"mutations":{"nuc":[]}},"name":"USA/UT-UPHL-210729773882/2021|MZ746543.1|2021-07-16","node_attrs":{"MAT_Clade_0":{"value":""},"MAT_Clade_1":{"value":""},"cluster":{"value":"node_18294"},"country":{"value":"USA"},"date":{"value":"2021-07-16"},"div":42}},{"branch_attrs":{"labels":{"cluster":"node_18294","nuc mutations":"","sample":"USA/UT-UPHL-210729773882/2021|MZ770581.1|2021-07-16"},"mutations":{"nuc":[]}},"name":"USA/UT-UPHL-210729773882/2021|MZ770581.1|2021-07-16","node_attrs":{"MAT_Clade_0":{"value":""},"MAT_Clade_1":{"value":""},"cluster":{"value":"node_18294"},"country":{"value":"USA"},"date":{"value":"2021-07-16"},"div":42}},{"branch_attrs":{"labels":{"cluster":"node_18294","nuc mutations":"","sample":"USA/UT-UPHL-210731381479/2021|MZ769440.1|2021-07-19"},"mutations":{"nuc":[]}},"name":"USA/UT-UPHL-210731381479/2021|MZ769440.1|2021-07-19","node_attrs":{"MAT_Clade_0":{"value":""},"MAT_Clade_1":{"value":""},"cluster":{"value":"node_18294"},"country":{"value":"USA"},"date":{"value":"2021-07-19"},"div":42}},{"branch_attrs":{"labels":{"cluster":"node_18294","nuc mutations":"","sample":"USA/UT-UPHL-210806721590/2021|MZ835103.1|2021-07-23"},"mutations":{"nuc":[]}},"name":"USA/UT-UPHL-210806721590/2021|MZ835103.1|2021-07-23","node_attrs":{"MAT_Clade_0":{"value":""},"MAT_Clade_1":{"value":""},"cluster":{"value":"node_18294"},"country":{"value":"USA"},"date":{"value":"2021-07-23"},"div":42}},{"branch_attrs":{"labels":{"nuc mutations":"A7163G,C23248T","sample":"node_18298"},"mutations":{"nuc":["A7163G","C23248T"]}},"children":[{"branch_attrs":{"labels":{"cluster":"node_18294","nuc mutations":"","sample":"USA/UT-UPHL-210729029113/2021|MZ746159.1|2021-07-19"},"mutations":{"nuc":[]}},"name":"USA/UT-UPHL-210729029113/2021|MZ746159.1|2021-07-19","node_attrs":{"MAT_Clade_0":{"value":""},"MAT_Clade_1":{"value":""},"cluster":{"value":"node_18294"},"country":{"value":"USA"},"date":{"value":"2021-07-19"},"div":44}},{"branch_attrs":{"labels":{"cluster":"node_18294","nuc mutations":"","sample":"USA/UT-UPHL-210729029113/2021|MZ770195.1|2021-07-19"},"mutations":{"nuc":[]}},"name":"USA/UT-UPHL-210729029113/2021|MZ770195.1|2021-07-19","node_attrs":{"MAT_Clade_0":{"value":""},"MAT_Clade_1":{"value":""},"cluster":{"value":"node_18294"},"country":{"value":"USA"},"date":{"value":"2021-07-19"},"div":44}}],"name":"node_18298","node_attrs":{"div":44}}],"name":"node_18297","node_attrs":{"div":42}}],"name":"node_18295","node_attrs":{"div":41}}],"name":"node_18294","node_attrs":{"div":40}}],"name":"wrapper"},"version":"v2"}
