{"meta":{"colorings":[{"key":"country","title":"Country","type":"categorical"},{"key":"cluster","title":"cluster","type":"categorical"}],"description":"JSON generated by matUtils. If you have metadata you wish to display, you can now drag on a CSV/TSV file and it will be added into this view, [see here](https://docs.nextstrain.org/projects/auspice/en/latest/advanced-functionality/drag-drop-csv-tsv.html) for more info.","display_defaults":{"branch_label":"none"},"filters":["country"],"panels":["tree"],"title":"mutation_annotated_tree"},"tree":{"children":[{"branch_attrs":{"labels":{"nuc mutations":"G210T,C241T,C1191T,C1267T,C3037T,C5184T,C6027A,G9203A,T9678C,C11005A,C14408T,C16915T,A17496G,A20396G,C21618G,A21792C,T22917G,C22995A,A23403G,C23604G,C23613T,G24410A,C25469T,T26767C,T27638C,C27752T,A28461G,G28881T,G29402T,G29742T","sample":"node_6200"},"mutations":{"nuc":["G210T","C241T","C1191T","C1267T","C3037T","C5184T","C6027A","G9203A","T9678C","C11005A","C14408T","C16915T","A17496G","A20396G","C21618G","A21792C","T22917G","C22995A","A23403G","C23604G","C23613T","G24410A","C25469T","T26767C","T27638C","C27752T","A28461G","G28881T","G29402T","G29742T"]}},"children":[{"branch_attrs":{"labels":{"cluster":"node_6200","nuc mutations":"C17463T","sample":"USA/AL-CDC-LC0081777/2021|MZ554029.1|2021-06-23"},"mutations":{"nuc":["C17463T"]}},"name":"USA/AL-CDC-LC0081777/2021|MZ554029.1|2021-06-23","node_attrs":{"MAT_Clade_0":{"value":""},"MAT_Clade_1":{"value":""},"cluster":{"value":"node_6200"},"country":{"value":"USA"},"date":{"value":"2021-06-23"},"div":31}},{"branch_attrs":{"labels":{"cluster":"node_6200","nuc mutations":"G26506T","sample":"USA/AL-CDC-LC0089728/2021|MZ591563.1|2021-07-01"},"mutations":{"nuc":["G26506T"]}},"name":"USA/AL-CDC-LC0089728/2021|MZ591563.1|2021-07-01","node_attrs":{"MAT_Clade_0":{"value":""},"MAT_Clade_1":{"value":""},"cluster":{"value":"node_6200"},"country":{"value":"USA"},"date":{"value":"2021-07-01"},"div":31}},{"branch_attrs":{"labels":{"cluster":"node_6200","nuc mutations":"G27967T","sample":"USA/AL-CDC-ASC210113118/2021|MZ745874.1|2021-07-10"},"mutations":{"nuc":["G27967T"]}},"name":"USA/AL-CDC-ASC210113118/2021|MZ745874.1|2021-07-10","node_attrs":{"MAT_Clade_0":{"value":""},"MAT_Clade_1":{"value":""},"cluster":{"value":"node_6200"},"country":{"value":"USA"},"date":{"value":"2021-07-10"},"div":31}},{"branch_attrs":{"labels":{"nuc mutations":"C3784T","sample":"USA/GA-CDC-ASC210160269/2021|MZ743938.1|2021-07-19"},"mutations":{"nuc":["C3784T"]}},"name":"USA/GA-CDC-ASC210160269/2021|MZ743938.1|2021-07-19","node_attrs":{"MAT_Clade_0":{"value":""},"MAT_Clade_1":{"value":""},"country":{"value":"USA"},"date":{"value":"2021-07-19"},"div":31}},{"branch_attrs":{"labels":{"cluster":"node_6200","nuc mutations":"C21855T","sample":"USA/AL-UAB-GX503/2021|MZ822440.1|2021-07-18"},"mutations":{"nuc":["C21855T"]}},"name":"USA/AL-UAB-GX503/2021|MZ822440.1|2021-07-18","node_attrs":{"MAT_Clade_0":{"value":""},"MAT_Clade_1":{"value":""},"cluster":{"value":"node_6200"},"country":{"value":"USA"},"date":{"value":"2021-07-18"},"div":31}},{"branch_attrs":{"labels":{"cluster":"node_6200","nuc mutations":"C2455T,C3425T","sample":"USA/AL-UAB-GX505/2021|MZ822442.1|2021-07-16"},"mutations":{"nuc":["C2455T","C3425T"]}},"name":"USA/AL-UAB-GX505/2021|MZ822442.1|2021-07-16","node_attrs":{"MAT_Clade_0":{"value":""},"MAT_Clade_1":{"value":""},"cluster":{"value":"node_6200"},"country":{"value":"USA"},"date":{"value":"2021-07-16"},"div":32}},{"branch_attrs":{"labels":{"cluster":"node_6200","nuc mutations":"C486T","sample":"USA/AL-UAB-GX704/2021|MZ828149.1|2021-08-04"},"mutations":{"nuc":["C486T"]}},"name":"USA/AL-UAB-GX704/2021|MZ828149.1|2021-08-04","node_attrs":{"MAT_Clade_0":{"value":""},"MAT_Clade_1":{"value":""},"cluster":{"value":"node_6200"},"country":{"value":"USA"},"date":{"value":"2021-08-04"},"div":31}},{"branch_attrs":{"labels":{"nuc mutations":"C15600A","sample":"USA/CT-CDC-QDX26380805/2021|MZ714984.1|2021-06-28"},"mutations":{"nuc":["C15600A"]}},"name":"USA/CT-CDC-QDX26380805/2021|MZ714984.1|2021-06-28","node_attrs":{"MAT_Clade_0":{"value":""},"MAT_Clade_1":{"value":""},"country":{"value":"USA"},"date":{"value":"2021-06-28"},"div":31}},{"branch_attrs":{"labels":{"nuc mutations":"","sample":"USA/FL-CDC-QDX26118094/2021|MZ530780.1|2021-06-18"},"mutations":{"nuc":[]}},"name":"USA/FL-CDC-QDX26118094/2021|MZ530780.1|2021-06-18","node_attrs":{"MAT_Clade_0":{"value":""},"MAT_Clade_1":{"value":""},"country":{"value":"USA"},"date":{"value":"2021-06-18"},"div":30}},{"branch_attrs":{"labels":{"cluster":"node_6200","nuc mutations":"","sample":"USA/AL-CDC-LC0081965/2021|MZ554067.1|2021-06-24"},"mutations":{"nuc":[]}},"name":"USA/AL-CDC-LC0081965/2021|MZ554067.1|2021-06-24","node_attrs":{"MAT_Clade_0":{"value":""},"MAT_Clade_1":{"value":""},"cluster":{"value":"node_6200"},"country":{"value":"USA"},"date":{"value":"2021-06-24"},"div":30}},{"branch_attrs":{"labels":{"cluster":"node_6200","nuc mutations":"","sample":"USA/AL-UAB-GX388/2021|MZ567278.1|2021-06-29"},"mutations":{"nuc":[]}},"name":"USA/AL-UAB-GX388/2021|MZ567278.1|2021-06-29","node_attrs":{"MAT_Clade_0":{"value":""},"MAT_Clade_1":{"value":""},"cluster":{"value":"node_6200"},"country":{"value":"USA"},"date":{"value":"2021-06-29"},"div":30}},{"branch_attrs":{"labels":{"cluster":"node_6200","nuc mutations":"","sample":"USA/AL-UAB-GX384/2021|MZ567274.1|2021-06-27"},"mutations":{"nuc":[]}},"name":"USA/AL-UAB-GX384/2021|MZ567274.1|2021-06-27","node_attrs":{"MAT_Clade_0":{"value":""},"MAT_Clade_1":{"value":""},"cluster":{"value":"node_6200"},"country":{"value":"USA"},"date":{"value":"2021-06-27"},"div":30}},{"branch_attrs":{"labels":{"cluster":"node_6200","nuc mutations":"","sample":"USA/AL-UAB-GX432/2021|MZ574415.1|2021-07-08"},"mutations":{"nuc":[]}},"name":"USA/AL-UAB-GX432/2021|MZ574415.1|2021-07-08","node_attrs":{"MAT_Clade_0":{"value":""},"MAT_Clade_1":{"value":""},"cluster":{"value":"node_6200"},"country":{"value":"USA"},"date":{"value":"2021-07-08"},"div":30}},{"branch_attrs":{"labels":{"cluster":"node_6200","nuc mutations":"","sample":"USA/AL-UAB-GX422/2021|MZ571863.1|2021-07-06"},"mutations":{"nuc":[]}},"name":"USA/AL-UAB-GX422/2021|MZ571863.1|2021-07-06","node_attrs":{"MAT_Clade_0":{"value":""},"MAT_Clade_1":{"value":""},"cluster":{"value":"node_6200"},"country":{"value":"USA"},"date":{"value":"2021-07-06"},"div":30}},{"branch_attrs":{"labels":{"cluster":"node_6200","nuc mutations":"","sample":"USA/AL-UAB-GX443/2021|MZ574425.1|2021-07-12"},"mutations":{"nuc":[]}},"name":"USA/AL-UAB-GX443/2021|MZ574425.1|2021-07-12","node_attrs":{"MAT_Clade_0":{"value":""},"MAT_Clade_1":{"value":""},"cluster":{"value":"node_6200"},"country":{"value":"USA"},"date":{"value":"2021-07-12"},"div":30}},{"branch_attrs":{"labels":{"cluster":"node_6200","nuc mutations":"","sample":"USA/AL-CDC-FG-054891/2021|MZ760675.1|2021-07-27"},"mutations":{"nuc":[]}},"name":"USA/AL-CDC-FG-054891/2021|MZ760675.1|2021-07-27","node_attrs":{"MAT_Clade_0":{"value":""},"MAT_Clade_1":{"value":""},"cluster":{"value":"node_6200"},"country":{"value":"USA"},"date":{"value":"2021-07-27"},"div":30}},{"branch_attrs":{"labels":{"nuc mutations":"C8640T","sample":"node_6207"},"mutations":{"nuc":["C8640T"]}},"children":[{"branch_attrs":{"labels":{"cluster":"node_6200","nuc mutations":"A11005C","sample":"USA/AL-CDC-ASC210154892/2021|MZ729067.1|2021-06-27"},"mutations":{"nuc":["A11005C"]}},"name":"USA/AL-CDC-ASC210154892/2021|MZ729067.1|2021-06-27","node_attrs":{"MAT_Clade_0":{"value":""},"MAT_Clade_1":{"value":""},"cluster":{"value":"node_6200"},"country":{"value":"USA"},"date":{"value":"2021-06-27"},"div":32}},{"branch_attrs":{"labels":{"cluster":"node_6200","nuc mutations":"C27638T,T29742G","sample":"USA/AL-CDC-ASC210109693/2021|MZ566155.1|2021-06-16"},"mutations":{"nuc":["C27638T","T29742G"]}},"name":"USA/AL-CDC-ASC210109693/2021|MZ566155.1|2021-06-16","node_attrs":{"MAT_Clade_0":{"value":""},"MAT_Clade_1":{"value":""},"cluster":{"value":"node_6200"},"country":{"value":"USA"},"date":{"value":"2021-06-16"},"div":33}}],"name":"node_6207","node_attrs":{"div":31}},{"branch_attrs":{"labels":{"nuc mutations":"C6310T","sample":"node_6208"},"mutations":{"nuc":["C6310T"]}},"children":[{"branch_attrs":{"labels":{"nuc mutations":"","sample":"USA/FL-CDC-LC0100400/2021|MZ787071.1|2021-07-17"},"mutations":{"nuc":[]}},"name":"USA/FL-CDC-LC0100400/2021|MZ787071.1|2021-07-17","node_attrs":{"MAT_Clade_0":{"value":""},"MAT_Clade_1":{"value":""},"country":{"value":"USA"},"date":{"value":"2021-07-17"},"div":31}},{"branch_attrs":{"labels":{"nuc mutations":"","sample":"USA/FL-CDC-LC0100389/2021|MZ787026.1|2021-07-16"},"mutations":{"nuc":[]}},"name":"USA/FL-CDC-LC0100389/2021|MZ787026.1|2021-07-16","node_attrs":{"MAT_Clade_0":{"value":""},"MAT_Clade_1":{"value":""},"country":{"value":"USA"},"date":{"value":"2021-07-16"},"div":31}}],"name":"node_6208","node_attrs":{"div":31}},{"branch_attrs":{"labels":{"nuc mutations":"A2421G","sample":"node_6209"},"mutations":{"nuc":["A2421G"]}},"children":[{"branch_attrs":{"labels":{"cluster":"node_6200","nuc mutations":"","sample":"USA/AL-CDC-2-4718301/2021|MZ828283.1|2021-07-26"},"mutations":{"nuc":[]}},"name":"USA/AL-CDC-2-4718301/2021|MZ828283.1|2021-07-26","node_attrs":{"MAT_Clade_0":{"value":""},"MAT_Clade_1":{"value":""},"cluster":{"value":"node_6200"},"country":{"value":"USA"},"date":{"value":"2021-07-26"},"div":31}},{"branch_attrs":{"labels":{"cluster":"node_6200","nuc mutations":"","sample":"USA/AL-CDC-2-4718301/2021|MZ828522.1|2021-07-26"},"mutations":{"nuc":[]}},"name":"USA/AL-CDC-2-4718301/2021|MZ828522.1|2021-07-26","node_attrs":{"MAT_Clade_0":{"value":""},"MAT_Clade_1":{"value":""},"cluster":{"value":"node_6200"},"country":{"value":"USA"},"date":{"value":"2021-07-26"},"div":31}}],"name":"node_6209","node_attrs":{"div":31}},{"branch_attrs":{"labels":{"nuc mutations":"C6031T","sample":"node_6206"},"mutations":{"nuc":["C6031T"]}},"children":[{"branch_attrs":{"labels":{"cluster":"node_6200","nuc mutations":"C6040T","sample":"USA/AL-UAB-GX501/2021|MZ822438.1|2021-07-16"},"mutations":{"nuc":["C6040T"]}},"name":"USA/AL-UAB-GX501/2021|MZ822438.1|2021-07-16","node_attrs":{"MAT_Clade_0":{"value":""},"MAT_Clade_1":{"value":""},"cluster":{"value":"node_6200"},"country":{"value":"USA"},"date":{"value":"2021-07-16"},"div":32}},{"branch_attrs":{"labels":{"cluster":"node_6200","nuc mutations":"","sample":"USA/AL-CDC-LC0098932/2021|MZ786318.1|2021-07-12"},"mutations":{"nuc":[]}},"name":"USA/AL-CDC-LC0098932/2021|MZ786318.1|2021-07-12","node_attrs":{"MAT_Clade_0":{"value":""},"MAT_Clade_1":{"value":""},"cluster":{"value":"node_6200"},"country":{"value":"USA"},"date":{"value":"2021-07-12"},"div":31}},{"branch_attrs":{"labels":{"cluster":"node_6200","nuc mutations":"","sample":"USA/AL-CDC-LC0098860/2021|MZ786117.1|2021-07-13"},"mutations":{"nuc":[]}},"name":"USA/AL-CDC-LC0098860/2021|MZ786117.1|2021-07-13","node_attrs":{"MAT_Clade_0":{"value":""},"MAT_Clade_1":{"value":""},"cluster":{"value":"node_6200"},"country":{"value":"USA"},"date":{"value":"2021-07-13"},"div":31}}],"name":"node_6206","node_attrs":{"div":31}},{"branch_attrs":{"labels":{"nuc mutations":"A11830G","sample":"node_6201"},"mutations":{"nuc":["A11830G"]}},"children":[{"branch_attrs":{"labels":{"cluster":"node_6200","nuc mutations":"C203T,C7528T,C27610T,C28290T","sample":"USA/AL-UAB-GX708/2021|MZ828153.1|2021-08-04"},"mutations":{"nuc":["C203T","C7528T","C27610T","C28290T"]}},"name":"USA/AL-UAB-GX708/2021|MZ828153.1|2021-08-04","node_attrs":{"MAT_Clade_0":{"value":""},"MAT_Clade_1":{"value":""},"cluster":{"value":"node_6200"},"country":{"value":"USA"},"date":{"value":"2021-08-04"},"div":35}},{"branch_attrs":{"labels":{"cluster":"node_6200","nuc mutations":"C274T","sample":"USA/AL-UAB-GX457/2021|MZ710408.1|2021-07-13"},"mutations":{"nuc":["C274T"]}},"name":"USA/AL-UAB-GX457/2021|MZ710408.1|2021-07-13","node_attrs":{"MAT_Clade_0":{"value":""},"MAT_Clade_1":{"value":""},"cluster":{"value":"node_6200"},"country":{"value":"USA"},"date":{"value":"2021-07-13"},"div":32}},{"branch_attrs":{"labels":{"cluster":"node_6200","nuc mutations":"G3328T,C6363T,C23809T,C27513T","sample":"USA/AL-UAB-GX714/2021|MZ828158.1|2021-08-05"},"mutations":{"nuc":["G3328T","C6363T","C23809T","C27513T"]}},"name":"USA/AL-UAB-GX714/2021|MZ828158.1|2021-08-05","node_attrs":{"MAT_Clade_0":{"value":""},"MAT_Clade_1":{"value":""},"cluster":{"value":"node_6200"},"country":{"value":"USA"},"date":{"value":"2021-08-05"},"div":35}},{"branch_attrs":{"labels":{"nuc mutations":"","sample":"USA/KS-CDC-LC0109727/2021|MZ785828.1|2021-07-09"},"mutations":{"nuc":[]}},"name":"USA/KS-CDC-LC0109727/2021|MZ785828.1|2021-07-09","node_attrs":{"MAT_Clade_0":{"value":""},"MAT_Clade_1":{"value":""},"country":{"value":"USA"},"date":{"value":"2021-07-09"},"div":31}},{"branch_attrs":{"labels":{"cluster":"node_6200","nuc mutations":"","sample":"USA/AL-UAB-GX541/2021|MZ827618.1|2021-07-21"},"mutations":{"nuc":[]}},"name":"USA/AL-UAB-GX541/2021|MZ827618.1|2021-07-21","node_attrs":{"MAT_Clade_0":{"value":""},"MAT_Clade_1":{"value":""},"cluster":{"value":"node_6200"},"country":{"value":"USA"},"date":{"value":"2021-07-21"},"div":31}},{"branch_attrs":{"labels":{"cluster":"node_6200","nuc mutations":"","sample":"USA/AL-UAB-GX548/2021|MZ827625.1|2021-07-21"},"mutations":{"nuc":[]}},"name":"USA/AL-UAB-GX548/2021|MZ827625.1|2021-07-21","node_attrs":{"MAT_Clade_0":{"value":""},"MAT_Clade_1":{"value":""},"cluster":{"value":"node_6200"},"country":{"value":"USA"},"date":{"value":"2021-07-21"},"div":31}},{"branch_attrs":{"labels":{"nuc mutations":"G8516A,G25552T","sample":"node_6205"},"mutations":{"nuc":["G8516A","G25552T"]}},"children":[{"branch_attrs":{"labels":{"cluster":"node_6200","nuc mutations":"","sample":"USA/AL-CDC-FG-071904/2021|MZ837840.1|2021-08-08"},"mutations":{"nuc":[]}},"name":"USA/AL-CDC-FG-071904/2021|MZ837840.1|2021-08-08","node_attrs":{"MAT_Clade_0":{"value":""},"MAT_Clade_1":{"value":""},"cluster":{"value":"node_6200"},"country":{"value":"USA"},"date":{"value":"2021-08-08"},"div":33}},{"branch_attrs":{"labels":{"cluster":"node_6200","nuc mutations":"","sample":"USA/AL-CDC-FG-071904/2021|MZ837488.1|2021-08-08"},"mutations":{"nuc":[]}},"name":"USA/AL-CDC-FG-071904/2021|MZ837488.1|2021-08-08","node_attrs":{"MAT_Clade_0":{"value":""},"MAT_Clade_1":{"value":""},"cluster":{"value":"node_6200"},"country":{"value":"USA"},"date":{"value":"2021-08-08"},"div":33}}],"name":"node_6205","node_attrs":{"div":33}},{"branch_attrs":{"labels":{"nuc mutations":"C8016T,C22458T","sample":"node_6203"},"mutations":{"nuc":["C8016T","C22458T"]}},"children":[{"branch_attrs":{"labels":{"nuc mutations":"","sample":"USA/TX-CDC-FG-048260/2021|MZ730702.1|2021-07-19"},"mutations":{"nuc":[]}},"name":"USA/TX-CDC-FG-048260/2021|MZ730702.1|2021-07-19","node_attrs":{"MAT_Clade_0":{"value":""},"MAT_Clade_1":{"value":""},"country":{"value":"USA"},"date":{"value":"2021-07-19"},"div":33}},{"branch_attrs":{"labels":{"nuc mutations":"","sample":"USA/CA-CDC-FG-048116/2021|MZ730442.1|2021-07-25"},"mutations":{"nuc":[]}},"name":"USA/CA-CDC-FG-048116/2021|MZ730442.1|2021-07-25","node_attrs":{"MAT_Clade_0":{"value":""},"MAT_Clade_1":{"value":""},"country":{"value":"USA"},"date":{"value":"2021-07-25"},"div":33}},{"branch_attrs":{"labels":{"nuc mutations":"","sample":"USA/CA-CDC-FG-053275/2021|MZ740380.1|2021-07-26"},"mutations":{"nuc":[]}},"name":"USA/CA-CDC-FG-053275/2021|MZ740380.1|2021-07-26","node_attrs":{"MAT_Clade_0":{"value":""},"MAT_Clade_1":{"value":""},"country":{"value":"USA"},"date":{"value":"2021-07-26"},"div":33}}],"name":"node_6203","node_attrs":{"div":33}},{"branch_attrs":{"labels":{"nuc mutations":"A11005C","sample":"node_6204"},"mutations":{"nuc":["A11005C"]}},"children":[{"branch_attrs":{"labels":{"nuc mutations":"","sample":"USA/NC-CDC-ASC210114508/2021|MZ745371.1|2021-07-12"},"mutations":{"nuc":[]}},"name":"USA/NC-CDC-ASC210114508/2021|MZ745371.1|2021-07-12","node_attrs":{"MAT_Clade_0":{"value":""},"MAT_Clade_1":{"value":""},"country":{"value":"USA"},"date":{"value":"2021-07-12"},"div":32}},{"branch_attrs":{"labels":{"cluster":"node_6200","nuc mutations":"G677A","sample":"USA/AL-CDC-ASC210161026/2021|MZ744218.1|2021-07-18"},"mutations":{"nuc":["G677A"]}},"name":"USA/AL-CDC-ASC210161026/2021|MZ744218.1|2021-07-18","node_attrs":{"MAT_Clade_0":{"value":""},"MAT_Clade_1":{"value":""},"cluster":{"value":"node_6200"},"country":{"value":"USA"},"date":{"value":"2021-07-18"},"div":33}},{"branch_attrs":{"labels":{"cluster":"node_6200","nuc mutations":"C18795T,A24410G,C29284T","sample":"USA/AL-CDC-ASC210160272/2021|MZ743940.1|2021-07-17"},"mutations":{"nuc":["C18795T","A24410G","C29284T"]}},"name":"USA/AL-CDC-ASC210160272/2021|MZ743940.1|2021-07-17","node_attrs":{"MAT_Clade_0":{"value":""},"MAT_Clade_1":{"value":""},"cluster":{"value":"node_6200"},"country":{"value":"USA"},"date":{"value":"2021-07-17"},"div":35}}],"name":"node_6204","node_attrs":{"div":32}},{"branch_attrs":{"labels":{"nuc mutations":"T5028C","sample":"node_6202"},"mutations":{"nuc":["T5028C"]}},"children":[{"branch_attrs":{"labels":{"cluster":"node_6200","nuc mutations":"C22858T","sample":"USA/AL-CDC-FG-062053/2021|MZ764142.1|2021-07-30"},"mutations":{"nuc":["C22858T"]}},"name":"USA/AL-CDC-FG-062053/2021|MZ764142.1|2021-07-30","node_attrs":{"MAT_Clade_0":{"value":""},"MAT_Clade_1":{"value":""},"cluster":{"value":"node_6200"},"country":{"value":"USA"},"date":{"value":"2021-07-30"},"div":33}},{"branch_attrs":{"labels":{"cluster":"node_6200","nuc mutations":"T7407C","sample":"USA/AL-CDC-FG-048213/2021|MZ730545.1|2021-07-18"},"mutations":{"nuc":["T7407C"]}},"name":"USA/AL-CDC-FG-048213/2021|MZ730545.1|2021-07-18","node_attrs":{"MAT_Clade_0":{"value":""},"MAT_Clade_1":{"value":""},"cluster":{"value":"node_6200"},"country":{"value":"USA"},"date":{"value":"2021-07-18"},"div":33}},{"branch_attrs":{"labels":{"nuc mutations":"","sample":"USA/SD-CDC-2-4679457/2021|MZ723557.1|2021-07-23"},"mutations":{"nuc":[]}},"name":"USA/SD-CDC-2-4679457/2021|MZ723557.1|2021-07-23","node_attrs":{"MAT_Clade_0":{"value":""},"MAT_Clade_1":{"value":""},"country":{"value":"USA"},"date":{"value":"2021-07-23"},"div":32}},{"branch_attrs":{"labels":{"cluster":"node_6200","nuc mutations":"","sample":"USA/AL-UAB-GX451/2021|MZ710402.1|2021-07-12"},"mutations":{"nuc":[]}},"name":"USA/AL-UAB-GX451/2021|MZ710402.1|2021-07-12","node_attrs":{"MAT_Clade_0":{"value":""},"MAT_Clade_1":{"value":""},"cluster":{"value":"node_6200"},"country":{"value":"USA"},"date":{"value":"2021-07-12"},"div":32}},{"branch_attrs":{"labels":{"cluster":"node_6200","nuc mutations":"","sample":"USA/AL-CDC-FG-048196/2021|MZ730544.1|2021-07-18"},"mutations":{"nuc":[]}},"name":"USA/AL-CDC-FG-048196/2021|MZ730544.1|2021-07-18","node_attrs":{"MAT_Clade_0":{"value":""},"MAT_Clade_1":{"value":""},"cluster":{"value":"node_6200"},"country":{"value":"USA"},"date":{"value":"2021-07-18"},"div":32}},{"branch_attrs":{"labels":{"cluster":"node_6200","nuc mutations":"","sample":"USA/AL-CDC-ASC210157917/2021|MZ743094.1|2021-07-16"},"mutations":{"nuc":[]}},"name":"USA/AL-CDC-ASC210157917/2021|MZ743094.1|2021-07-16","node_attrs":{"MAT_Clade_0":{"value":""},"MAT_Clade_1":{"value":""},"cluster":{"value":"node_6200"},"country":{"value":"USA"},"date":{"value":"2021-07-16"},"div":32}},{"branch_attrs":{"labels":{"cluster":"node_6200","nuc mutations":"","sample":"USA/AL-CDC-FG-062091/2021|MZ764148.1|2021-07-30"},"mutations":{"nuc":[]}},"name":"USA/AL-CDC-FG-062091/2021|MZ764148.1|2021-07-30","node_attrs":{"MAT_Clade_0":{"value":""},"MAT_Clade_1":{"value":""},"cluster":{"value":"node_6200"},"country":{"value":"USA"},"date":{"value":"2021-07-30"},"div":32}},{"branch_attrs":{"labels":{"nuc mutations":"","sample":"USA/GA-CDC-ASC210160847/2021|MZ744371.1|2021-07-20"},"mutations":{"nuc":[]}},"name":"USA/GA-CDC-ASC210160847/2021|MZ744371.1|2021-07-20","node_attrs":{"MAT_Clade_0":{"value":""},"MAT_Clade_1":{"value":""},"country":{"value":"USA"},"date":{"value":"2021-07-20"},"div":32}},{"branch_attrs":{"labels":{"cluster":"node_6200","nuc mutations":"","sample":"USA/AL-CDC-FG-046730/2021|MZ727119.1|2021-07-17"},"mutations":{"nuc":[]}},"name":"USA/AL-CDC-FG-046730/2021|MZ727119.1|2021-07-17","node_attrs":{"MAT_Clade_0":{"value":""},"MAT_Clade_1":{"value":""},"cluster":{"value":"node_6200"},"country":{"value":"USA"},"date":{"value":"2021-07-17"},"div":32}},{"branch_attrs":{"labels":{"cluster":"node_6200","nuc mutations":"","sample":"USA/AL-CDC-LC0109581/2021|MZ785790.1|2021-07-09"},"mutations":{"nuc":[]}},"name":"USA/AL-CDC-LC0109581/2021|MZ785790.1|2021-07-09","node_attrs":{"MAT_Clade_0":{"value":""},"MAT_Clade_1":{"value":""},"cluster":{"value":"node_6200"},"country":{"value":"USA"},"date":{"value":"2021-07-09"},"div":32}},{"branch_attrs":{"labels":{"cluster":"node_6200","nuc mutations":"","sample":"USA/AL-UAB-GX544/2021|MZ827621.1|2021-07-21"},"mutations":{"nuc":[]}},"name":"USA/AL-UAB-GX544/2021|MZ827621.1|2021-07-21","node_attrs":{"MAT_Clade_0":{"value":""},"MAT_Clade_1":{"value":""},"cluster":{"value":"node_6200"},"country":{"value":"USA"},"date":{"value":"2021-07-21"},"div":32}}],"name":"node_6202","node_attrs":{"div":32}}],"name":"node_6201","node_attrs":{"div":31}}],"name":"node_6200","node_attrs":{"div":30}}],"name":"wrapper"},"version":"v2"}
