{"meta":{"colorings":[{"key":"country","title":"Country","type":"categorical"},{"key":"cluster","title":"cluster","type":"categorical"}],"description":"JSON generated by matUtils. If you have metadata you wish to display, you can now drag on a CSV/TSV file and it will be added into this view, [see here](https://docs.nextstrain.org/projects/auspice/en/latest/advanced-functionality/drag-drop-csv-tsv.html) for more info.","display_defaults":{"branch_label":"none"},"filters":["country"],"panels":["tree"],"title":"mutation_annotated_tree"},"tree":{"children":[{"branch_attrs":{"labels":{"nuc mutations":"G210T,C241T,A1098G,T2911G,C3037T,C5184T,A5584G,T7292C,C9891T,T11418C,C11514T,C13019T,C14408T,G15451A,C16466T,A20437G,C21618G,C22227T,T22917G,C22995A,A23403G,C23604G,G24410A,A24783G,G25352T,C25469T,T26767C,A27345T,G27506T,T27638C,C27752T,G28300T,A28461G,G28881T,G29402T,G29706T,G29742T","sample":"node_11874"},"mutations":{"nuc":["G210T","C241T","A1098G","T2911G","C3037T","C5184T","A5584G","T7292C","C9891T","T11418C","C11514T","C13019T","C14408T","G15451A","C16466T","A20437G","C21618G","C22227T","T22917G","C22995A","A23403G","C23604G","G24410A","A24783G","G25352T","C25469T","T26767C","A27345T","G27506T","T27638C","C27752T","G28300T","A28461G","G28881T","G29402T","G29706T","G29742T"]}},"children":[{"branch_attrs":{"labels":{"nuc mutations":"G29795A","sample":"USA/CA-CDC-FG-038573/2021|MZ492576.1|2021-06-23"},"mutations":{"nuc":["G29795A"]}},"name":"USA/CA-CDC-FG-038573/2021|MZ492576.1|2021-06-23","node_attrs":{"MAT_Clade_0":{"value":""},"MAT_Clade_1":{"value":""},"country":{"value":"USA"},"date":{"value":"2021-06-23"},"div":38}},{"branch_attrs":{"labels":{"nuc mutations":"C26907T","sample":"USA/WA-S9455/2021|MZ513872.1|2021-06-26"},"mutations":{"nuc":["C26907T"]}},"name":"USA/WA-S9455/2021|MZ513872.1|2021-06-26","node_attrs":{"MAT_Clade_0":{"value":""},"MAT_Clade_1":{"value":""},"country":{"value":"USA"},"date":{"value":"2021-06-26"},"div":38}},{"branch_attrs":{"labels":{"nuc mutations":"C934T","sample":"USA/FL-CDC-QDX26344096/2021|MZ716343.1|2021-06-26"},"mutations":{"nuc":["C934T"]}},"name":"USA/FL-CDC-QDX26344096/2021|MZ716343.1|2021-06-26","node_attrs":{"MAT_Clade_0":{"value":""},"MAT_Clade_1":{"value":""},"country":{"value":"USA"},"date":{"value":"2021-06-26"},"div":38}},{"branch_attrs":{"labels":{"nuc mutations":"C9286T","sample":"USA/NV-NSPHL-LV377632/2021|MZ643783.1|2021-07-13"},"mutations":{"nuc":["C9286T"]}},"name":"USA/NV-NSPHL-LV377632/2021|MZ643783.1|2021-07-13","node_attrs":{"MAT_Clade_0":{"value":""},"MAT_Clade_1":{"value":""},"country":{"value":"USA"},"date":{"value":"2021-07-13"},"div":38}},{"branch_attrs":{"labels":{"nuc mutations":"A21612G","sample":"USA/NV-CDC-QDX26531909/2021|MZ655698.1|2021-07-06"},"mutations":{"nuc":["A21612G"]}},"name":"USA/NV-CDC-QDX26531909/2021|MZ655698.1|2021-07-06","node_attrs":{"MAT_Clade_0":{"value":""},"MAT_Clade_1":{"value":""},"country":{"value":"USA"},"date":{"value":"2021-07-06"},"div":38}},{"branch_attrs":{"labels":{"nuc mutations":"T28120C","sample":"USA/CA-CDC-FG-047116/2021|MZ696832.1|2021-07-22"},"mutations":{"nuc":["T28120C"]}},"name":"USA/CA-CDC-FG-047116/2021|MZ696832.1|2021-07-22","node_attrs":{"MAT_Clade_0":{"value":""},"MAT_Clade_1":{"value":""},"country":{"value":"USA"},"date":{"value":"2021-07-22"},"div":38}},{"branch_attrs":{"labels":{"nuc mutations":"T28867C","sample":"USA/NY-CDC-FG-043940/2021|MZ699968.1|2021-07-12"},"mutations":{"nuc":["T28867C"]}},"name":"USA/NY-CDC-FG-043940/2021|MZ699968.1|2021-07-12","node_attrs":{"MAT_Clade_0":{"value":""},"MAT_Clade_1":{"value":""},"country":{"value":"USA"},"date":{"value":"2021-07-12"},"div":38}},{"branch_attrs":{"labels":{"nuc mutations":"G28628T,T29685C","sample":"USA/CA-CDC-FG-043674/2021|MZ699713.1|2021-07-16"},"mutations":{"nuc":["G28628T","T29685C"]}},"name":"USA/CA-CDC-FG-043674/2021|MZ699713.1|2021-07-16","node_attrs":{"MAT_Clade_0":{"value":""},"MAT_Clade_1":{"value":""},"country":{"value":"USA"},"date":{"value":"2021-07-16"},"div":39}},{"branch_attrs":{"labels":{"cluster":"USA/WI-CDC-FG-062276/2021|MZ802231.1|2021-08-03","nuc mutations":"","sample":"USA/WI-CDC-FG-062276/2021|MZ802231.1|2021-08-03"},"mutations":{"nuc":[]}},"name":"USA/WI-CDC-FG-062276/2021|MZ802231.1|2021-08-03","node_attrs":{"MAT_Clade_0":{"value":""},"MAT_Clade_1":{"value":""},"cluster":{"value":"USA/WI-CDC-FG-062276/2021|MZ802231.1|2021-08-03"},"country":{"value":"USA"},"date":{"value":"2021-08-03"},"div":37}},{"branch_attrs":{"labels":{"nuc mutations":"T13019C","sample":"node_11875"},"mutations":{"nuc":["T13019C"]}},"children":[{"branch_attrs":{"labels":{"nuc mutations":"C17010T","sample":"USA/UT-UPHL-210811424031/2021|MZ817790.1|2021-07-29"},"mutations":{"nuc":["C17010T"]}},"name":"USA/UT-UPHL-210811424031/2021|MZ817790.1|2021-07-29","node_attrs":{"MAT_Clade_0":{"value":""},"MAT_Clade_1":{"value":""},"country":{"value":"USA"},"date":{"value":"2021-07-29"},"div":39}},{"branch_attrs":{"labels":{"nuc mutations":"","sample":"USA/WA-S9445/2021|MZ513864.1|2021-06-24"},"mutations":{"nuc":[]}},"name":"USA/WA-S9445/2021|MZ513864.1|2021-06-24","node_attrs":{"MAT_Clade_0":{"value":""},"MAT_Clade_1":{"value":""},"country":{"value":"USA"},"date":{"value":"2021-06-24"},"div":38}}],"name":"node_11875","node_attrs":{"div":38}},{"branch_attrs":{"labels":{"nuc mutations":"A10699G","sample":"node_11883"},"mutations":{"nuc":["A10699G"]}},"children":[{"branch_attrs":{"labels":{"nuc mutations":"","sample":"USA/WA-CDC-LC0091541/2021|MZ592337.1|2021-06-28"},"mutations":{"nuc":[]}},"name":"USA/WA-CDC-LC0091541/2021|MZ592337.1|2021-06-28","node_attrs":{"MAT_Clade_0":{"value":""},"MAT_Clade_1":{"value":""},"country":{"value":"USA"},"date":{"value":"2021-06-28"},"div":38}},{"branch_attrs":{"labels":{"nuc mutations":"","sample":"USA/FL-CDC-LC0085984/2021|MZ554791.1|2021-06-25"},"mutations":{"nuc":[]}},"name":"USA/FL-CDC-LC0085984/2021|MZ554791.1|2021-06-25","node_attrs":{"MAT_Clade_0":{"value":""},"MAT_Clade_1":{"value":""},"country":{"value":"USA"},"date":{"value":"2021-06-25"},"div":38}}],"name":"node_11883","node_attrs":{"div":38}},{"branch_attrs":{"labels":{"nuc mutations":"G702A,C9857T","sample":"node_11886"},"mutations":{"nuc":["G702A","C9857T"]}},"children":[{"branch_attrs":{"labels":{"nuc mutations":"A3372G","sample":"USA/CA-CDC-FG-044782/2021|MZ697914.1|2021-07-19"},"mutations":{"nuc":["A3372G"]}},"name":"USA/CA-CDC-FG-044782/2021|MZ697914.1|2021-07-19","node_attrs":{"MAT_Clade_0":{"value":""},"MAT_Clade_1":{"value":""},"country":{"value":"USA"},"date":{"value":"2021-07-19"},"div":40}},{"branch_attrs":{"labels":{"nuc mutations":"","sample":"USA/CA-CDC-FG-044601/2021|MZ697893.1|2021-07-19"},"mutations":{"nuc":[]}},"name":"USA/CA-CDC-FG-044601/2021|MZ697893.1|2021-07-19","node_attrs":{"MAT_Clade_0":{"value":""},"MAT_Clade_1":{"value":""},"country":{"value":"USA"},"date":{"value":"2021-07-19"},"div":39}}],"name":"node_11886","node_attrs":{"div":39}},{"branch_attrs":{"labels":{"nuc mutations":"C1713T","sample":"node_11884"},"mutations":{"nuc":["C1713T"]}},"children":[{"branch_attrs":{"labels":{"nuc mutations":"G11801T,C25688T","sample":"USA/CA-CDC-FG-045705/2021|MZ697784.1|2021-07-19"},"mutations":{"nuc":["G11801T","C25688T"]}},"name":"USA/CA-CDC-FG-045705/2021|MZ697784.1|2021-07-19","node_attrs":{"MAT_Clade_0":{"value":""},"MAT_Clade_1":{"value":""},"country":{"value":"USA"},"date":{"value":"2021-07-19"},"div":40}},{"branch_attrs":{"labels":{"nuc mutations":"T16587C,C20480T","sample":"USA/CA-CDC-FG-056854/2021|MZ765729.1|2021-07-31"},"mutations":{"nuc":["T16587C","C20480T"]}},"name":"USA/CA-CDC-FG-056854/2021|MZ765729.1|2021-07-31","node_attrs":{"MAT_Clade_0":{"value":""},"MAT_Clade_1":{"value":""},"country":{"value":"USA"},"date":{"value":"2021-07-31"},"div":40}},{"branch_attrs":{"labels":{"nuc mutations":"G20750T","sample":"USA/NV-CDC-QDX27169267/2021|MZ796699.1|2021-07-25"},"mutations":{"nuc":["G20750T"]}},"name":"USA/NV-CDC-QDX27169267/2021|MZ796699.1|2021-07-25","node_attrs":{"MAT_Clade_0":{"value":""},"MAT_Clade_1":{"value":""},"country":{"value":"USA"},"date":{"value":"2021-07-25"},"div":39}},{"branch_attrs":{"labels":{"nuc mutations":"T27752C","sample":"USA/UT-UPHL-210731227753/2021|MZ769423.1|2021-07-20"},"mutations":{"nuc":["T27752C"]}},"name":"USA/UT-UPHL-210731227753/2021|MZ769423.1|2021-07-20","node_attrs":{"MAT_Clade_0":{"value":""},"MAT_Clade_1":{"value":""},"country":{"value":"USA"},"date":{"value":"2021-07-20"},"div":39}},{"branch_attrs":{"labels":{"nuc mutations":"","sample":"USA/CA-CDC-FG-043804/2021|MZ699800.1|2021-07-16"},"mutations":{"nuc":[]}},"name":"USA/CA-CDC-FG-043804/2021|MZ699800.1|2021-07-16","node_attrs":{"MAT_Clade_0":{"value":""},"MAT_Clade_1":{"value":""},"country":{"value":"USA"},"date":{"value":"2021-07-16"},"div":38}},{"branch_attrs":{"labels":{"nuc mutations":"","sample":"USA/CA-CDC-FG-047270/2021|MZ696948.1|2021-07-22"},"mutations":{"nuc":[]}},"name":"USA/CA-CDC-FG-047270/2021|MZ696948.1|2021-07-22","node_attrs":{"MAT_Clade_0":{"value":""},"MAT_Clade_1":{"value":""},"country":{"value":"USA"},"date":{"value":"2021-07-22"},"div":38}},{"branch_attrs":{"labels":{"nuc mutations":"","sample":"USA/CA-CDC-FG-044389/2021|MZ697817.1|2021-07-19"},"mutations":{"nuc":[]}},"name":"USA/CA-CDC-FG-044389/2021|MZ697817.1|2021-07-19","node_attrs":{"MAT_Clade_0":{"value":""},"MAT_Clade_1":{"value":""},"country":{"value":"USA"},"date":{"value":"2021-07-19"},"div":38}},{"branch_attrs":{"labels":{"nuc mutations":"","sample":"USA/CA-CDC-FG-045497/2021|MZ697683.1|2021-07-19"},"mutations":{"nuc":[]}},"name":"USA/CA-CDC-FG-045497/2021|MZ697683.1|2021-07-19","node_attrs":{"MAT_Clade_0":{"value":""},"MAT_Clade_1":{"value":""},"country":{"value":"USA"},"date":{"value":"2021-07-19"},"div":38}},{"branch_attrs":{"labels":{"nuc mutations":"","sample":"USA/MA-CDCBI-CRSP_ZGEIOG5BN26TQHZB/2021|MZ753376.1|2021-08-01"},"mutations":{"nuc":[]}},"name":"USA/MA-CDCBI-CRSP_ZGEIOG5BN26TQHZB/2021|MZ753376.1|2021-08-01","node_attrs":{"MAT_Clade_0":{"value":""},"MAT_Clade_1":{"value":""},"country":{"value":"USA"},"date":{"value":"2021-08-01"},"div":38}},{"branch_attrs":{"labels":{"nuc mutations":"","sample":"USA/MA-CDCBI-CRSP_KSJJFHG4OMRC5KA5/2021|MZ753149.1|2021-08-02"},"mutations":{"nuc":[]}},"name":"USA/MA-CDCBI-CRSP_KSJJFHG4OMRC5KA5/2021|MZ753149.1|2021-08-02","node_attrs":{"MAT_Clade_0":{"value":""},"MAT_Clade_1":{"value":""},"country":{"value":"USA"},"date":{"value":"2021-08-02"},"div":38}},{"branch_attrs":{"labels":{"nuc mutations":"C1913T,G28178T","sample":"node_11885"},"mutations":{"nuc":["C1913T","G28178T"]}},"children":[{"branch_attrs":{"labels":{"nuc mutations":"","sample":"USA/CA-CDC-FG-041086/2021|MZ729566.1|2021-07-09"},"mutations":{"nuc":[]}},"name":"USA/CA-CDC-FG-041086/2021|MZ729566.1|2021-07-09","node_attrs":{"MAT_Clade_0":{"value":""},"MAT_Clade_1":{"value":""},"country":{"value":"USA"},"date":{"value":"2021-07-09"},"div":40}},{"branch_attrs":{"labels":{"nuc mutations":"","sample":"USA/NV-CDC-QDX26574449/2021|MZ650052.1|2021-07-07"},"mutations":{"nuc":[]}},"name":"USA/NV-CDC-QDX26574449/2021|MZ650052.1|2021-07-07","node_attrs":{"MAT_Clade_0":{"value":""},"MAT_Clade_1":{"value":""},"country":{"value":"USA"},"date":{"value":"2021-07-07"},"div":40}}],"name":"node_11885","node_attrs":{"div":40}}],"name":"node_11884","node_attrs":{"div":38}},{"branch_attrs":{"labels":{"nuc mutations":"G4223T","sample":"node_11876"},"mutations":{"nuc":["G4223T"]}},"children":[{"branch_attrs":{"labels":{"nuc mutations":"G25302T","sample":"USA/CA-CDC-FG-041992/2021|MZ696315.1|2021-07-12"},"mutations":{"nuc":["G25302T"]}},"name":"USA/CA-CDC-FG-041992/2021|MZ696315.1|2021-07-12","node_attrs":{"MAT_Clade_0":{"value":""},"MAT_Clade_1":{"value":""},"country":{"value":"USA"},"date":{"value":"2021-07-12"},"div":39}},{"branch_attrs":{"labels":{"nuc mutations":"A26928G","sample":"USA/CA-LACPHL-AF01634/2021|MZ723259.1|2021-07-04"},"mutations":{"nuc":["A26928G"]}},"name":"USA/CA-LACPHL-AF01634/2021|MZ723259.1|2021-07-04","node_attrs":{"MAT_Clade_0":{"value":""},"MAT_Clade_1":{"value":""},"country":{"value":"USA"},"date":{"value":"2021-07-04"},"div":39}},{"branch_attrs":{"labels":{"nuc mutations":"","sample":"USA/CA-CDC-FG-040561/2021|MZ593147.1|2021-07-07"},"mutations":{"nuc":[]}},"name":"USA/CA-CDC-FG-040561/2021|MZ593147.1|2021-07-07","node_attrs":{"MAT_Clade_0":{"value":""},"MAT_Clade_1":{"value":""},"country":{"value":"USA"},"date":{"value":"2021-07-07"},"div":38}},{"branch_attrs":{"labels":{"nuc mutations":"","sample":"USA/NV-NSPHL-LV369648/2021|MZ597647.1|2021-07-02"},"mutations":{"nuc":[]}},"name":"USA/NV-NSPHL-LV369648/2021|MZ597647.1|2021-07-02","node_attrs":{"MAT_Clade_0":{"value":""},"MAT_Clade_1":{"value":""},"country":{"value":"USA"},"date":{"value":"2021-07-02"},"div":38}},{"branch_attrs":{"labels":{"nuc mutations":"","sample":"USA/NV-NSPHL-LV371079/2021|MZ597656.1|2021-07-06"},"mutations":{"nuc":[]}},"name":"USA/NV-NSPHL-LV371079/2021|MZ597656.1|2021-07-06","node_attrs":{"MAT_Clade_0":{"value":""},"MAT_Clade_1":{"value":""},"country":{"value":"USA"},"date":{"value":"2021-07-06"},"div":38}},{"branch_attrs":{"labels":{"nuc mutations":"","sample":"USA/CA-CDC-LC0102091/2021|MZ783973.1|2021-07-11"},"mutations":{"nuc":[]}},"name":"USA/CA-CDC-LC0102091/2021|MZ783973.1|2021-07-11","node_attrs":{"MAT_Clade_0":{"value":""},"MAT_Clade_1":{"value":""},"country":{"value":"USA"},"date":{"value":"2021-07-11"},"div":38}},{"branch_attrs":{"labels":{"nuc mutations":"","sample":"USA/NV-NSPHL-LV384846/2021|MZ769695.1|2021-07-20"},"mutations":{"nuc":[]}},"name":"USA/NV-NSPHL-LV384846/2021|MZ769695.1|2021-07-20","node_attrs":{"MAT_Clade_0":{"value":""},"MAT_Clade_1":{"value":""},"country":{"value":"USA"},"date":{"value":"2021-07-20"},"div":38}},{"branch_attrs":{"labels":{"nuc mutations":"C1960T","sample":"node_11880"},"mutations":{"nuc":["C1960T"]}},"children":[{"branch_attrs":{"labels":{"nuc mutations":"","sample":"USA/NV-CDC-QDX26531921/2021|MZ655544.1|2021-07-05"},"mutations":{"nuc":[]}},"name":"USA/NV-CDC-QDX26531921/2021|MZ655544.1|2021-07-05","node_attrs":{"MAT_Clade_0":{"value":""},"MAT_Clade_1":{"value":""},"country":{"value":"USA"},"date":{"value":"2021-07-05"},"div":39}},{"branch_attrs":{"labels":{"nuc mutations":"","sample":"USA/NV-CDC-QDX26446127/2021|MZ591149.1|2021-07-02"},"mutations":{"nuc":[]}},"name":"USA/NV-CDC-QDX26446127/2021|MZ591149.1|2021-07-02","node_attrs":{"MAT_Clade_0":{"value":""},"MAT_Clade_1":{"value":""},"country":{"value":"USA"},"date":{"value":"2021-07-02"},"div":39}}],"name":"node_11880","node_attrs":{"div":39}},{"branch_attrs":{"labels":{"nuc mutations":"C27213T","sample":"node_11881"},"mutations":{"nuc":["C27213T"]}},"children":[{"branch_attrs":{"labels":{"nuc mutations":"","sample":"USA/NV-CDC-QDX27127613/2021|MZ797009.1|2021-07-24"},"mutations":{"nuc":[]}},"name":"USA/NV-CDC-QDX27127613/2021|MZ797009.1|2021-07-24","node_attrs":{"MAT_Clade_0":{"value":""},"MAT_Clade_1":{"value":""},"country":{"value":"USA"},"date":{"value":"2021-07-24"},"div":39}},{"branch_attrs":{"labels":{"nuc mutations":"G18318T","sample":"node_11882"},"mutations":{"nuc":["G18318T"]}},"children":[{"branch_attrs":{"labels":{"nuc mutations":"","sample":"USA/CA-CDC-FG-042041/2021|MZ696285.1|2021-07-12"},"mutations":{"nuc":[]}},"name":"USA/CA-CDC-FG-042041/2021|MZ696285.1|2021-07-12","node_attrs":{"MAT_Clade_0":{"value":""},"MAT_Clade_1":{"value":""},"country":{"value":"USA"},"date":{"value":"2021-07-12"},"div":40}},{"branch_attrs":{"labels":{"nuc mutations":"","sample":"USA/CA-CDC-FG-041991/2021|MZ696305.1|2021-07-12"},"mutations":{"nuc":[]}},"name":"USA/CA-CDC-FG-041991/2021|MZ696305.1|2021-07-12","node_attrs":{"MAT_Clade_0":{"value":""},"MAT_Clade_1":{"value":""},"country":{"value":"USA"},"date":{"value":"2021-07-12"},"div":40}}],"name":"node_11882","node_attrs":{"div":40}}],"name":"node_11881","node_attrs":{"div":39}},{"branch_attrs":{"labels":{"nuc mutations":"G19101T,C29803T","sample":"node_11877"},"mutations":{"nuc":["G19101T","C29803T"]}},"children":[{"branch_attrs":{"labels":{"nuc mutations":"C27847T","sample":"USA/NV-NSPHL-LV371138/2021|MZ597661.1|2021-07-06"},"mutations":{"nuc":["C27847T"]}},"name":"USA/NV-NSPHL-LV371138/2021|MZ597661.1|2021-07-06","node_attrs":{"MAT_Clade_0":{"value":""},"MAT_Clade_1":{"value":""},"country":{"value":"USA"},"date":{"value":"2021-07-06"},"div":41}},{"branch_attrs":{"labels":{"nuc mutations":"","sample":"USA/NJ-CDC-LC0110851/2021|MZ785125.1|2021-07-18"},"mutations":{"nuc":[]}},"name":"USA/NJ-CDC-LC0110851/2021|MZ785125.1|2021-07-18","node_attrs":{"MAT_Clade_0":{"value":""},"MAT_Clade_1":{"value":""},"country":{"value":"USA"},"date":{"value":"2021-07-18"},"div":40}},{"branch_attrs":{"labels":{"nuc mutations":"","sample":"IMS-10150-CVDP-C5C1B0E2-68B1-4390-A865-7BD4B4179978|OU516165.1|2021-07-24"},"mutations":{"nuc":[]}},"name":"IMS-10150-CVDP-C5C1B0E2-68B1-4390-A865-7BD4B4179978|OU516165.1|2021-07-24","node_attrs":{"div":40}},{"branch_attrs":{"labels":{"nuc mutations":"","sample":"IMS-10150-CVDP-95528EFB-D1D8-4854-BB39-75948A98765E|OU516291.1|2021-07-27"},"mutations":{"nuc":[]}},"name":"IMS-10150-CVDP-95528EFB-D1D8-4854-BB39-75948A98765E|OU516291.1|2021-07-27","node_attrs":{"div":40}},{"branch_attrs":{"labels":{"nuc mutations":"","sample":"USA/OH-UHTL-1148/2021|MZ831339.1|2021-08-06"},"mutations":{"nuc":[]}},"name":"USA/OH-UHTL-1148/2021|MZ831339.1|2021-08-06","node_attrs":{"MAT_Clade_0":{"value":""},"MAT_Clade_1":{"value":""},"country":{"value":"USA"},"date":{"value":"2021-08-06"},"div":40}},{"branch_attrs":{"labels":{"nuc mutations":"","sample":"USA/PA-M21075128/2021|MZ827065.1|2021-07-22"},"mutations":{"nuc":[]}},"name":"USA/PA-M21075128/2021|MZ827065.1|2021-07-22","node_attrs":{"MAT_Clade_0":{"value":""},"MAT_Clade_1":{"value":""},"country":{"value":"USA"},"date":{"value":"2021-07-22"},"div":40}},{"branch_attrs":{"labels":{"nuc mutations":"G19999T","sample":"node_11878"},"mutations":{"nuc":["G19999T"]}},"children":[{"branch_attrs":{"labels":{"nuc mutations":"","sample":"USA/MA-CDCBI-CRSP_V5VJ7B2P3O4T6NBT/2021|MZ675295.1|2021-07-25"},"mutations":{"nuc":[]}},"name":"USA/MA-CDCBI-CRSP_V5VJ7B2P3O4T6NBT/2021|MZ675295.1|2021-07-25","node_attrs":{"MAT_Clade_0":{"value":""},"MAT_Clade_1":{"value":""},"country":{"value":"USA"},"date":{"value":"2021-07-25"},"div":41}},{"branch_attrs":{"labels":{"nuc mutations":"","sample":"USA/MA-CDCBI-CRSP_2IB7NMWYMIIHCPIM/2021|MZ669506.1|2021-07-21"},"mutations":{"nuc":[]}},"name":"USA/MA-CDCBI-CRSP_2IB7NMWYMIIHCPIM/2021|MZ669506.1|2021-07-21","node_attrs":{"MAT_Clade_0":{"value":""},"MAT_Clade_1":{"value":""},"country":{"value":"USA"},"date":{"value":"2021-07-21"},"div":41}}],"name":"node_11878","node_attrs":{"div":41}},{"branch_attrs":{"labels":{"nuc mutations":"C17304T","sample":"node_11879"},"mutations":{"nuc":["C17304T"]}},"children":[{"branch_attrs":{"labels":{"nuc mutations":"","sample":"USA/AL-CDC-FG-054608/2021|MZ760621.1|2021-07-26"},"mutations":{"nuc":[]}},"name":"USA/AL-CDC-FG-054608/2021|MZ760621.1|2021-07-26","node_attrs":{"MAT_Clade_0":{"value":""},"MAT_Clade_1":{"value":""},"country":{"value":"USA"},"date":{"value":"2021-07-26"},"div":41}},{"branch_attrs":{"labels":{"nuc mutations":"","sample":"USA/AL-CDC-FG-052886/2021|MZ731814.1|2021-07-26"},"mutations":{"nuc":[]}},"name":"USA/AL-CDC-FG-052886/2021|MZ731814.1|2021-07-26","node_attrs":{"MAT_Clade_0":{"value":""},"MAT_Clade_1":{"value":""},"country":{"value":"USA"},"date":{"value":"2021-07-26"},"div":41}},{"branch_attrs":{"labels":{"nuc mutations":"","sample":"USA/AL-CDC-FG-062025/2021|MZ764181.1|2021-07-29"},"mutations":{"nuc":[]}},"name":"USA/AL-CDC-FG-062025/2021|MZ764181.1|2021-07-29","node_attrs":{"MAT_Clade_0":{"value":""},"MAT_Clade_1":{"value":""},"country":{"value":"USA"},"date":{"value":"2021-07-29"},"div":41}}],"name":"node_11879","node_attrs":{"div":41}}],"name":"node_11877","node_attrs":{"div":40}}],"name":"node_11876","node_attrs":{"div":38}}],"name":"node_11874","node_attrs":{"div":37}}],"name":"wrapper"},"version":"v2"}
